<root>
  <color_pass>
    <blend type="transparent" />
    <material max_insts="2048" vertex_shader="Default2DVertexShader" pixel_shader="ColorPixelShaderNoClip">
      <shader_resources>
        <item name="Texture0" filename="textures/orb.png" />
      </shader_resources>
      <samplers>
        <item name="LinearSampler" />
      </samplers>
    </material>
  </color_pass>
  <occlusion_pass>
    <blend type="add" />
    <material max_insts="2048" vertex_shader="Default2DVertexShader" pixel_shader="OcclusionTextureAlphaPixelShaderNoClip">
      <shader_resources>
        <item name="Texture0" filename="textures/orb1.png" />
      </shader_resources>
      <samplers>
        <item name="LinearSampler" />
      </samplers>
    </material>
  </occlusion_pass>
</root>